.gitignore
.travis.yml
CHANGELOG.md
CONTRIBUTING.md
COPYING
Dockerfile-debian
Dockerfile-redhat
README.md
Singularity
docker-compose.yml
formatters.py
readthedocs.yml
reproman.cfg
requirements-devel.txt
requirements.txt
setup.cfg
setup.py
setup_support.py
tox.ini
docs/Makefile
docs/source/acknowledgements.rst
docs/source/background.rst
docs/source/cmdline.rst
docs/source/conf.py
docs/source/execute.rst
docs/source/glossary.rst
docs/source/index.rst
docs/source/manage.rst
docs/source/modref.rst
docs/source/related.rst
docs/source/_static/reproman_logo.png
docs/source/_templates/autosummary/module.rst
docs/source/sandbox/ReproNim Entities.png
docs/source/sandbox/ReproNim Entities.xml
docs/source/sandbox/hierarchy.rst
docs/source/sandbox/packages.rst
docs/source/usecases/index.rst
reproman/__init__.py
reproman/api.py
reproman/cmd.py
reproman/config.py
reproman/conftest.py
reproman/consts.py
reproman/dochelpers.py
reproman/log.py
reproman/utils.py
reproman/version.py
reproman.egg-info/PKG-INFO
reproman.egg-info/SOURCES.txt
reproman.egg-info/dependency_links.txt
reproman.egg-info/entry_points.txt
reproman.egg-info/requires.txt
reproman.egg-info/top_level.txt
reproman/cmdline/__init__.py
reproman/cmdline/common_args.py
reproman/cmdline/helpers.py
reproman/cmdline/main.py
reproman/cmdline/tests/__init__.py
reproman/cmdline/tests/test_helpers.py
reproman/distributions/__init__.py
reproman/distributions/base.py
reproman/distributions/conda.py
reproman/distributions/debian.py
reproman/distributions/docker.py
reproman/distributions/neurodebian.py
reproman/distributions/piputils.py
reproman/distributions/redhat.py
reproman/distributions/singularity.py
reproman/distributions/vcs.py
reproman/distributions/venv.py
reproman/distributions/tests/__init__.py
reproman/distributions/tests/test_conda.py
reproman/distributions/tests/test_debian.py
reproman/distributions/tests/test_distribution.py
reproman/distributions/tests/test_docker.py
reproman/distributions/tests/test_environment.py
reproman/distributions/tests/test_piputils.py
reproman/distributions/tests/test_redhat.py
reproman/distributions/tests/test_singularity.py
reproman/distributions/tests/test_vcs.py
