Metadata-Version: 2.1
Name: reproman
Version: 0.3.1
Summary: Neuroimaging Computational Environments Manager
Home-page: UNKNOWN
Author: The ReproMan Team and Contributors
Author-email: team@reproman.org
License: UNKNOWN
Platform: UNKNOWN
Requires-Python: >=3.6
Provides-Extra: aws
Provides-Extra: core
Provides-Extra: datalad
Provides-Extra: debian
Provides-Extra: devel
Provides-Extra: devel-docs
Provides-Extra: devel-neuroimaging
Provides-Extra: devel-utils
Provides-Extra: docker
Provides-Extra: full
Provides-Extra: full-except-datalad
Provides-Extra: meta
Provides-Extra: tests
